cce_agent/__init__.py
cce_agent/__main__.py
cce_agent/cli.py
src/__init__.py
src/__main__.py
src/agent.py
src/agent_testing_improvements.py
src/cli.py
src/config.py
src/config_loader.py
src/context_memory.py
src/context_resolver.py
src/mcp_integration.py
src/mcp_workflow.py
src/models.py
src/prompt_cache.py
src/repo_structure.txt
src/run_manifest.py
src/token_tracker.py
src/workspace_context.py
src/wrap_up_protocol.py
src/agent/__init__.py
src/agent/core.py
src/agent/state.py
src/agent/utils.py
src/agent/graphs/__init__.py
src/agent/graphs/execution.py
src/agent/graphs/planning.py
src/agent/phases/__init__.py
src/agent/phases/execution.py
src/agent/phases/planning.py
src/agent/tools/__init__.py
src/agent/tools/registry.py
src/analysis/__init__.py
src/analysis/cycle_report.py
src/analysis/empirical_questions.py
src/config/__init__.py
src/config/artifact_root.py
src/config/execution_limits.py
src/context_injection/__init__.py
src/context_injection/semantic_tagging.py
src/deep_agents/__init__.py
src/deep_agents/adr_integration_hook.py
src/deep_agents/advanced_patterns.py
src/deep_agents/audited_llm_wrapper.py
src/deep_agents/audited_post_hook.py
src/deep_agents/audited_tool_wrapper.py
src/deep_agents/cce_deep_agent.py
src/deep_agents/code_analyzer.py
src/deep_agents/command_safety.py
src/deep_agents/context_auditor.py
src/deep_agents/context_manager.py
src/deep_agents/cycle_tools.py
src/deep_agents/enable_auditing.py
src/deep_agents/fallback_systems.py
src/deep_agents/file_state.py
src/deep_agents/graph_wrappers.py
src/deep_agents/hybrid_filesystem_tools.py
src/deep_agents/mcp_ecosystem.py
src/deep_agents/mcp_integration.py
src/deep_agents/mcp_integration_enhancement.py
src/deep_agents/memory_hooks.py
src/deep_agents/memory_integration_validation.py
src/deep_agents/memory_nodes.py
src/deep_agents/memory_orchestrator.py
src/deep_agents/memory_recovery.py
src/deep_agents/memory_reducers.py
src/deep_agents/memory_serialization.py
src/deep_agents/memory_system_init.py
cce_agent-0.1.3.dist-info/METADATA
cce_agent-0.1.3.dist-info/WHEEL
cce_agent-0.1.3.dist-info/entry_points.txt
cce_agent-0.1.3.dist-info/top_level.txt
cce_agent-0.1.3.dist-info/RECORD
