Metadata-Version: 2.4
Name: cce-agent
Version: 0.1.3
Summary: Context-aware Code Evolution Agent - AI-powered code analysis and transformation
Author: jkbrooks
License: MIT
Project-URL: Homepage, https://github.com/jkbrooks/cce-agent
Project-URL: Repository, https://github.com/jkbrooks/cce-agent
Project-URL: Issues, https://github.com/jkbrooks/cce-agent/issues
Keywords: ai,agent,code-analysis,langchain,langgraph,llm
Classifier: Development Status :: 3 - Alpha
Classifier: Intended Audience :: Developers
Classifier: License :: OSI Approved :: MIT License
Classifier: Programming Language :: Python :: 3
Classifier: Programming Language :: Python :: 3.11
Classifier: Programming Language :: Python :: 3.12
Classifier: Topic :: Software Development :: Libraries :: Python Modules
Requires-Python: >=3.11
Requires-Dist: langchain<2.0.0,>=1.1.0
Requires-Dist: langchain-core<2.0.0,>=1.2.0
Requires-Dist: langchain-anthropic<2.0.0,>=1.2.0
Requires-Dist: langchain-openai<2.0.0,>=1.0.0
Requires-Dist: langchain-mcp-adapters>=0.1.0
Requires-Dist: langgraph<2.0.0,>=1.0.5
Requires-Dist: langgraph-checkpoint<4.0.0,>=2.1.0
Requires-Dist: langgraph-checkpoint-sqlite<4.0.0,>=2.1.0
Requires-Dist: anthropic
Requires-Dist: openai
Requires-Dist: deepagents>=0.3.1
Requires-Dist: tree-sitter>=0.20.0
Requires-Dist: tree-sitter-python>=0.20.0
Requires-Dist: tree-sitter-javascript>=0.20.0
Requires-Dist: tree-sitter-typescript>=0.20.0
Requires-Dist: aiohttp
Requires-Dist: requests
Requires-Dist: numpy
Requires-Dist: rich
Requires-Dist: langsmith
Requires-Dist: python-dotenv
Provides-Extra: dev
Requires-Dist: pytest>=8.0; extra == "dev"
Requires-Dist: pytest-asyncio>=0.24; extra == "dev"
Requires-Dist: coverage>=7.0; extra == "dev"
Requires-Dist: ruff>=0.8.0; extra == "dev"
Requires-Dist: mypy>=1.10; extra == "dev"
Requires-Dist: pre-commit>=4.0; extra == "dev"
Provides-Extra: legacy-dev
Requires-Dist: black; extra == "legacy-dev"
Requires-Dist: flake8; extra == "legacy-dev"
Provides-Extra: all
Requires-Dist: cce-agent[dev]; extra == "all"
Requires-Dist: cce-agent[legacy-dev]; extra == "all"
